subtitle_corrector_sdk/__init__.py
subtitle_corrector_sdk/config.json
subtitle_corrector_sdk/error_terms_library.json
subtitle_corrector_sdk/prompt.txt
subtitle_corrector_sdk/subtitle_corrector.py
subtitle_corrector_sdk-1.0.0.dist-info/METADATA
subtitle_corrector_sdk-1.0.0.dist-info/WHEEL
subtitle_corrector_sdk-1.0.0.dist-info/top_level.txt
subtitle_corrector_sdk-1.0.0.dist-info/RECORD
