Metadata-Version: 2.1
Name: subtitle_corrector_sdk
Version: 1.0.0
Summary: A package for correcting medical subtitles
Author: imuzhangy
Author-email: imuzhangying@gmail.com
Classifier: Programming Language :: Python :: 3
Classifier: License :: OSI Approved :: MIT License
Classifier: Operating System :: OS Independent
Requires-Python: >=3.6
Requires-Dist: requests
Requires-Dist: json
Requires-Dist: os
Requires-Dist: shutil
Requires-Dist: zipfile
Requires-Dist: datetime
Requires-Dist: logging
Requires-Dist: re
Requires-Dist: glob
Requires-Dist: pkg-resources
